utinyec/__init__.py
utinyec/cryptography.py
utinyec/cryptography_no_dependencies.py
utinyec/ec.py
utinyec/registry.py
utinyec/uVIPER_cryptography.py
utinyec-0.4.5.dist-info/LICENSE
utinyec-0.4.5.dist-info/METADATA
utinyec-0.4.5.dist-info/WHEEL
utinyec-0.4.5.dist-info/top_level.txt
utinyec-0.4.5.dist-info/RECORD
