Metadata-Version: 2.1
Name: utinyec
Version: 0.4.5
Summary: A tiny library to perform unverified elliptic curve cryptography (ECC) with arithmetic operations in pure micropython. Not security verified for production.
Home-page: https://github.com/JackLawrenceCRISPR/utinyec
Author: Jack Lawrence
Author-email: JackLawrenceCRISPR@gmail.com
License: aGPLv3
Keywords: elliptic,curves,crypto,tls,ssl,ecdhe,diffie-hellman
Classifier: Programming Language :: Python :: Implementation :: MicroPython
Requires: base64
Requires: hmac
License-File: LICENSE
